setup.py
TestRambo/__init__.py
TestRambo.egg-info/PKG-INFO
TestRambo.egg-info/SOURCES.txt
TestRambo.egg-info/dependency_links.txt
TestRambo.egg-info/not-zip-safe
TestRambo.egg-info/top_level.txt