Metadata-Version: 1.0
Name: TestRambo
Version: 0.1
Summary: Test like Rambo
Home-page: https://github.com/ashokesaha/TestRambo
Author: Ashoke Saha
Author-email: ashoke@rocketmail.com
License: MIT
Platform: UNKNOWN
